model_manager-0.8.data/data/settings.py
model_manager-0.8.data/scripts/mm
model_manager-0.8.data/scripts/modelmanager
modelmanager/__init__.py
modelmanager/commandline.py
modelmanager/project.py
modelmanager/settings.py
modelmanager/utils.py
modelmanager/plugins/__init__.py
modelmanager/plugins/clones.py
modelmanager/plugins/grass.py
modelmanager/plugins/pandas.py
modelmanager/plugins/templates.py
modelmanager/plugins/browser/__init__.py
modelmanager/plugins/browser/admin.py
modelmanager/plugins/browser/defaultsettings.py
modelmanager/plugins/browser/urls.py
modelmanager/plugins/browser/wsgi.py
modelmanager/plugins/browser/api/__init__.py
modelmanager/plugins/browser/api/admin.py
modelmanager/plugins/browser/api/models.py
modelmanager/plugins/browser/api/views.py
modelmanager/plugins/browser/api/migrations/0001_initial.py
modelmanager/plugins/browser/api/migrations/__init__.py
modelmanager/plugins/browser/api/static/api.js
modelmanager/plugins/browser/api/static/style.css
modelmanager/plugins/browser/api/static/api/function_list.css
modelmanager/plugins/browser/api/templates/admin/api/function/change_form.html
modelmanager/plugins/browser/api/templates/admin/api/function/change_list.html
modelmanager/plugins/browser/database/__init__.py
modelmanager/plugins/browser/database/admin.py
modelmanager/plugins/browser/database/admindefault.py
modelmanager/plugins/browser/database/models.py
modelmanager/plugins/browser/database/templates/admin/browser/run/change_form.html
modelmanager/plugins/browser/resources/__init__.py
modelmanager/plugins/browser/resources/admin.py
modelmanager/plugins/browser/resources/models.py
modelmanager/plugins/browser/resources/files/.gitkeep
modelmanager/plugins/browser/resources/migrations/__init__.py
modelmanager/resources/settings.py
modelmanager/scripts/mm
modelmanager/scripts/modelmanager
model_manager-0.8.dist-info/LICENSE.md
model_manager-0.8.dist-info/METADATA
model_manager-0.8.dist-info/WHEEL
model_manager-0.8.dist-info/top_level.txt
model_manager-0.8.dist-info/RECORD
