Metadata-Version: 2.2
Name: model-manager
Version: 0.8
Summary: A python package to manage your (scientific) model runs, input and output.
Home-page: https://github.com/mwort/modelmanager
Download-URL: https://github.com/mwort/modelmanager/tarball/0.8
Author: Michel Wortmann
Author-email: wortmann@pik-potsdam.de
License: BSD
Classifier: Development Status :: 3 - Alpha
Classifier: Intended Audience :: Developers
Classifier: Programming Language :: Python :: 2.7
License-File: LICENSE.md
Dynamic: author
Dynamic: author-email
Dynamic: classifier
Dynamic: description
Dynamic: description-content-type
Dynamic: download-url
Dynamic: home-page
Dynamic: keywords
Dynamic: license
Dynamic: summary
